{"defs":[{"_uid":"lh2vk0q0-0db6","_deleted":false,"_created":"lh2vk0q1","_updated":"lh2vk0q1","_tempCreated":"2023-04-29T22:51:20.233-05:00[America/Chicago]","_tempUpdated":"2023-04-29T22:51:20.233-05:00[America/Chicago]","_did":"0m7w","_lbl":"defOne","_desc":"This is now inerited","_emoji":"1️⃣","_scope":"SECOND"},{"_uid":"lh2vk0q3-0dtj","_deleted":true,"_created":"lh2vk0q3","_updated":"lh2vk3zl","_tempCreated":"2023-04-29T22:51:20.235-05:00[America/Chicago]","_tempUpdated":"2023-04-29T22:51:20.235-05:00[America/Chicago]","_did":"ay7l","_lbl":"TWO","_desc":"Scoped at an **hour**, cause why not have that option?","_emoji":"2️⃣","_scope":"HOUR"},{"_uid":"lh2vk0q4-0a06","_deleted":false,"_created":"lgvm3a11","_updated":"lh2vk0q4","_tempCreated":"2023-04-24T20:51:59.365-05:00[America/Chicago]","_tempUpdated":"2023-04-29T22:51:20.236-05:00[America/Chicago]","_did":"05a8","_lbl":"FREE","_desc":"Set a description","_emoji":"3️⃣","_scope":"DAY"},{"_uid":"lh2vk3zj-m9d6","_deleted":false,"_created":"lh2vk0q3","_updated":"lh2vk3zj","_tempCreated":"2023-04-29T22:51:20.235-05:00[America/Chicago]","_tempUpdated":"2023-04-29T22:51:24.463-05:00[America/Chicago]","_did":"ay7l","_lbl":"Two Relabeled","_desc":"Scoped at an **hour**, cause why not have that option?","_emoji":"2️⃣","_scope":"HOUR"}],"pointDefs":[{"_uid":"lh2vk0q2-ojke","_deleted":false,"_created":"lh2vk0q2","_updated":"lh2vk0q2","_tempCreated":"2023-04-29T22:51:20.234-05:00[America/Chicago]","_tempUpdated":"2023-04-29T22:51:20.234-05:00[America/Chicago]","_did":"0m7w","_pid":"8esq","_lbl":"Select Test","_desc":"For testing selects","_emoji":"⛏️","_type":"SELECT","_rollup":"COUNTOFEACH"},{"_uid":"lh2vk0q4-0o48","_deleted":false,"_created":"lh2vk0q4","_updated":"lh2vk0q4","_tempCreated":"2023-04-29T22:51:20.236-05:00[America/Chicago]","_tempUpdated":"2023-04-29T22:51:20.236-05:00[America/Chicago]","_did":"05a8","_pid":"0iu2","_lbl":"Free Item","_desc":"Set a description","_emoji":"🆓","_type":"TEXT","_rollup":"COUNT"},{"_uid":"lh2vk0q5-klza","_deleted":true,"_created":"lh2vk0q5","_updated":"lh2vk3zl","_tempCreated":"2023-04-29T22:51:20.237-05:00[America/Chicago]","_tempUpdated":"2023-04-29T22:51:20.237-05:00[America/Chicago]","_did":"ay7l","_pid":"0pc6","_lbl":"Numeric Thing","_desc":"Set a description","_emoji":"#️⃣","_type":"NUMBER","_rollup":"AVERAGE"},{"_uid":"lh2vk0q5-1wpj","_deleted":true,"_created":"lh2vk0q5","_updated":"lh2vk3zm","_tempCreated":"2023-04-29T22:51:20.237-05:00[America/Chicago]","_tempUpdated":"2023-04-29T22:51:20.237-05:00[America/Chicago]","_did":"ay7l","_pid":"0tb7","_lbl":"Boolean Thing","_desc":"Orig desc","_emoji":"👍","_type":"BOOL","_rollup":"COUNT"},{"_uid":"lh2vk3zk-dywe","_deleted":false,"_created":"lh2vk0q5","_updated":"lh2vk3zk","_tempCreated":"2023-04-29T22:51:20.237-05:00[America/Chicago]","_tempUpdated":"2023-04-29T22:51:24.464-05:00[America/Chicago]","_did":"ay7l","_pid":"0pc6","_lbl":"Test Relabel","_desc":"Set a description","_emoji":"#️⃣","_type":"NUMBER","_rollup":"AVERAGE"},{"_uid":"lh2vk3zl-r928","_deleted":false,"_created":"lh2vk0q5","_updated":"lh2vk3zm","_tempCreated":"2023-04-29T22:51:20.237-05:00[America/Chicago]","_tempUpdated":"2023-04-29T22:51:24.466-05:00[America/Chicago]","_did":"ay7l","_pid":"0tb7","_lbl":"Boolean Thing","_desc":"Orig desc","_emoji":"👎","_type":"BOOL","_rollup":"COUNT"}],"entries":[{"_uid":"lh2vk0q6-0m06","_deleted":true,"_created":"lh2vk0q6","_updated":"lh2vk3zp","_tempCreated":"2023-04-29T22:51:20.238-05:00[America/Chicago]","_tempUpdated":"2023-04-29T22:51:20.238-05:00[America/Chicago]","_eid":"lgricx7k-08al","_note":"Orig note","_did":"ay7l","_period":"2023-04-22T06","_source":""},{"_uid":"lh2vk0q7-0kef","_deleted":false,"_created":"lh2vk0q7","_updated":"lh2vk0q8","_tempCreated":"2023-04-29T22:51:20.239-05:00[America/Chicago]","_tempUpdated":"2023-04-29T22:51:20.24-05:00[America/Chicago]","_eid":"lh2vk0q8-3am6","_note":"","_did":"0m7w","_period":"2023-04-29T22:51:20","_source":""},{"_uid":"lh2vk3zm-097s","_deleted":false,"_created":"lh2vk0q6","_updated":"lh2vk3zn","_tempCreated":"2023-04-29T22:51:20.238-05:00[America/Chicago]","_tempUpdated":"2023-04-29T22:51:24.467-05:00[America/Chicago]","_eid":"lgricx7k-08al","_note":"Updated noted","_did":"ay7l","_period":"2023-04-22T06","_source":""}],"entryPoints":[{"_uid":"lh2vk0q6-idb9","_deleted":true,"_created":"lh2vk0q7","_updated":"lh2vk3zo","_tempCreated":"2023-04-29T22:51:20.239-05:00[America/Chicago]","_tempUpdated":"2023-04-29T22:51:20.239-05:00[America/Chicago]","_eid":"lgricx7k-08al","_pid":"0tb7","_val":false,"_did":"ay7l"},{"_uid":"lh2vk0q7-r0s5","_deleted":true,"_created":"lh2vk0q7","_updated":"lh2vk3zq","_tempCreated":"2023-04-29T22:51:20.239-05:00[America/Chicago]","_tempUpdated":"2023-04-29T22:51:20.239-05:00[America/Chicago]","_eid":"lgricx7k-08al","_pid":"0pc6","_val":5,"_did":"ay7l"},{"_uid":"lh2vk3zo-pwh7","_deleted":false,"_created":"lh2vk0q7","_updated":"lh2vk3zo","_tempCreated":"2023-04-29T22:51:20.239-05:00[America/Chicago]","_tempUpdated":"2023-04-29T22:51:24.468-05:00[America/Chicago]","_eid":"lgricx7k-08al","_pid":"0tb7","_val":true,"_did":"ay7l"},{"_uid":"lh2vk3zp-0p2f","_deleted":false,"_created":"lh2vk0q7","_updated":"lh2vk3zp","_tempCreated":"2023-04-29T22:51:20.239-05:00[America/Chicago]","_tempUpdated":"2023-04-29T22:51:24.469-05:00[America/Chicago]","_eid":"lgricx7k-08al","_pid":"0pc6","_val":6,"_did":"ay7l"}],"tagDefs":[{"_uid":"lh2vk0q9-0iha","_deleted":false,"_created":"lh2vk0q9","_updated":"lh2vk0q9","_tempCreated":"2023-04-29T22:51:20.241-05:00[America/Chicago]","_tempUpdated":"2023-04-29T22:51:20.241-05:00[America/Chicago]","_tid":"0x2q","_lbl":"My Tag!"},{"_uid":"lh2vk0q9-5k8p","_deleted":true,"_created":"lh2vk0q9","_updated":"lh2vk3zr","_tempCreated":"2023-04-29T22:51:20.241-05:00[America/Chicago]","_tempUpdated":"2023-04-29T22:51:20.241-05:00[America/Chicago]","_tid":"vvct","_lbl":"Orig Tag Label"},{"_uid":"lh2vk0qa-qbib","_deleted":false,"_created":"lh2vk0qa","_updated":"lh2vk0qa","_tempCreated":"2023-04-29T22:51:20.242-05:00[America/Chicago]","_tempUpdated":"2023-04-29T22:51:20.242-05:00[America/Chicago]","_tid":"0vvi","_lbl":"Select Option To Delete"},{"_uid":"lh2vk0qa-4x8q","_deleted":false,"_created":"lh2vk0qa","_updated":"lh2vk0qa","_tempCreated":"2023-04-29T22:51:20.242-05:00[America/Chicago]","_tempUpdated":"2023-04-29T22:51:20.242-05:00[America/Chicago]","_tid":"0vva","_lbl":"Select Option 1"},{"_uid":"lh2vk0qb-gn9e","_deleted":false,"_created":"lh2vk0qb","_updated":"lh2vk0qb","_tempCreated":"2023-04-29T22:51:20.243-05:00[America/Chicago]","_tempUpdated":"2023-04-29T22:51:20.243-05:00[America/Chicago]","_tid":"0vvb","_lbl":"Select Option 2"},{"_uid":"lh2vk3zq-j8yj","_deleted":false,"_created":"lh2vk0q9","_updated":"lh2vk3zq","_tempCreated":"2023-04-29T22:51:20.241-05:00[America/Chicago]","_tempUpdated":"2023-04-29T22:51:24.47-05:00[America/Chicago]","_tid":"vvct","_lbl":"New Label"}],"tags":[{"_uid":"lh2vk0qb-bq3o","_deleted":true,"_created":"lh2vk0qb","_updated":"lh2vk3zs","_tempCreated":"2023-04-29T22:51:20.243-05:00[America/Chicago]","_tempUpdated":"2023-04-29T22:51:20.243-05:00[America/Chicago]","_tid":"vvct","_did":"ay7l"},{"_uid":"lh2vk0qc-98am","_deleted":true,"_created":"lh2vk0qc","_updated":"lh2vk3zr","_tempCreated":"2023-04-29T22:51:20.244-05:00[America/Chicago]","_tempUpdated":"2023-04-29T22:51:20.244-05:00[America/Chicago]","_tid":"0vvi","_did":"0m7w","_pid":"8esq"},{"_uid":"lh2vk0qc-qss9","_deleted":false,"_created":"lh2vk0qc","_updated":"lh2vk0qc","_tempCreated":"2023-04-29T22:51:20.244-05:00[America/Chicago]","_tempUpdated":"2023-04-29T22:51:20.244-05:00[America/Chicago]","_tid":"0vva","_did":"0m7w","_pid":"8esq"},{"_uid":"lh2vk0qd-95rs","_deleted":false,"_created":"lh2vk0qd","_updated":"lh2vk0qd","_tempCreated":"2023-04-29T22:51:20.245-05:00[America/Chicago]","_tempUpdated":"2023-04-29T22:51:20.245-05:00[America/Chicago]","_tid":"0vvb","_did":"0m7w","_pid":"8esq"}],"overview":{"defs":{"current":3,"deleted":1},"pointDefs":{"current":4,"deleted":2},"entries":{"current":2,"deleted":1},"entryPoints":{"current":2,"deleted":2},"tagDefs":{"current":5,"deleted":1},"tags":{"current":2,"deleted":2},"lastUpdated":"lh2vk3zs"}}